[
  {
    "list": [
      "}"
    ],
    "template": "{cost"
  },
  {
    "list": [
      "}"
    ],
    "template": "{cost"
  },
  {
    "list": [
      "}"
    ],
    "template": "{cost"
  },
  {
    "list": [
      "}"
    ],
    "template": "{cost"
  },
  {
    "list": [
      "}"
    ],
    "template": "{cost"
  },
  {
    "list": [
      "}"
    ],
    "template": "{cost"
  },
  {
    "list": [
      "}"
    ],
    "template": "{cost"
  },
  {
    "list": [
      "0}"
    ],
    "template": "{cost"
  }
]