[
  {
    "list": [
      "}"
    ],
    "template": "{height"
  },
  {
    "list": [
      "500}"
    ],
    "template": "{height"
  },
  {
    "list": [
      "300}"
    ],
    "template": "{height"
  },
  {
    "list": [
      "300}"
    ],
    "template": "{height"
  },
  {
    "list": [
      "300}"
    ],
    "template": "{height"
  },
  {
    "list": [
      "300}"
    ],
    "template": "{height"
  },
  {
    "list": [
      "325}"
    ],
    "template": "{height"
  },
  {
    "list": [
      "300}"
    ],
    "template": "{height"
  },
  {
    "list": [
      "300}"
    ],
    "template": "{height"
  },
  {
    "list": [
      "300}"
    ],
    "template": "{height"
  },
  {
    "list": [
      "350}"
    ],
    "template": "{height"
  },
  {
    "list": [
      "300}"
    ],
    "template": "{height"
  }
]