[
  {
    "list": [
      "Alvijar",
      "elite",
      "MAJORS LAVA BADS AIR"
    ],
    "template": "anagram"
  },
  {
    "list": [
      "The Apothecary",
      "beginner",
      "CARPET AHOY"
    ],
    "template": "anagram"
  },
  {
    "list": [
      "Archmage Sedridor",
      "beginner",
      "CHAR GAME DISORDER"
    ],
    "template": "anagram"
  },
  {
    "list": [
      "Aretha",
      "medium",
      "A HEART"
    ],
    "template": "anagram"
  },
  {
    "list": [
      "King Awowogei",
      "hard",
      "WOO AN EGG KIWI"
    ],
    "template": "anagram"
  },
  {
    "list": [
      "Baraek",
      "medium",
      "A Baker"
    ],
    "template": "anagram"
  },
  {
    "list": [
      "Bolkoy",
      "hard",
      "BY LOOK"
    ],
    "template": "anagram"
  },
  {
    "list": [
      "Brambickle",
      "hard",
      "BAKER CLIMB"
    ],
    "template": "anagram"
  },
  {
    "list": [
      "Brian",
      "beginner",
      "IN BAR"
    ],
    "template": "anagram"
  },
  {
    "list": [
      "Brimstail",
      "medium",
      "BAIL TRIMS"
    ],
    "template": "anagram"
  },
  {
    "list": [
      "Brother Omad",
      "Hard",
      "Motherboard"
    ],
    "template": "anagram"
  },
  {
    "list": [
      "Brother Tranquility",
      "hard",
      "QUIT HORRIBLE TYRANT"
    ],
    "template": "anagram"
  },
  {
    "list": [
      "Brundt the Chieftain",
      "medium",
      "DT RUN B"
    ],
    "template": "anagram"
  },
  {
    "list": [
      "Cam",
      "elite",
      "MACHETE CLAM"
    ],
    "template": "anagram"
  },
  {
    "list": [
      "Cap'n Izzy No-Beard",
      "hard",
      "O BIRDZ A ZANY EN PC"
    ],
    "template": "anagram"
  },
  {
    "list": [
      "Captain Bruce",
      "master",
      "BRUCIE CATNAP"
    ],
    "template": "anagram"
  },
  {
    "list": [
      "Captain Ginea",
      "medium",
      "PACINNG A TAIE"
    ],
    "template": "anagram"
  },
  {
    "list": [
      "Tobias",
      "medium",
      "A BASIC ANTI POT"
    ],
    "template": "anagram"
  },
  {
    "list": [
      "Caroline",
      "medium",
      "ARC O LINE"
    ],
    "template": "anagram"
  },
  {
    "list": [
      "Charlie",
      "medium",
      "ARMCHAIR THE PELT"
    ],
    "template": "anagram"
  },
  {
    "list": [
      "Clerris",
      "medium",
      "R SLICER"
    ],
    "template": "anagram"
  },
  {
    "list": [
      "The cook",
      "medium",
      "OK CO"
    ],
    "template": "anagram"
  },
  {
    "list": [
      "Daer Krand",
      "hard",
      "DARN DRAKE"
    ],
    "template": "anagram"
  },
  {
    "list": [
      "Dark mage",
      "hard",
      "DEKAGRAM"
    ],
    "template": "anagram"
  },
  {
    "list": [
      "Dockmaster",
      "medium",
      "TAMED ROCKS"
    ],
    "template": "anagram"
  },
  {
    "list": [
      "Dominic Onion",
      "medium",
      "I DOOM ICON IN"
    ],
    "template": "anagram"
  },
  {
    "list": [
      "The Doomsayer",
      "hard",
      "DO SAY MORE"
    ],
    "template": "anagram"
  },
  {
    "list": [
      "Doric",
      "beginner",
      "I CORD"
    ],
    "template": "anagram"
  },
  {
    "list": [
      "Drunken Dwarf",
      "hard",
      "DR WARDEN FUNK"
    ],
    "template": "anagram"
  },
  {
    "list": [
      "Drunken soldier",
      "medium",
      "UESNKRL NRIEDDO"
    ],
    "template": "anagram"
  },
  {
    "list": [
      "Dugopul",
      "master",
      "DUO PLUG"
    ],
    "template": "anagram"
  },
  {
    "list": [
      "Dunstan",
      "medium",
      "Sand Nut"
    ],
    "template": "anagram"
  },
  {
    "list": [
      "Edmond",
      "medium",
      "NOD MED"
    ],
    "template": "anagram"
  },
  {
    "list": [
      "Edward",
      "master",
      "DED WAR"
    ],
    "template": "anagram"
  },
  {
    "list": [
      "Eohric",
      "medium",
      "HEORIC"
    ],
    "template": "anagram"
  },
  {
    "list": [
      "Evil Dave",
      "hard",
      "VEIL VEDA"
    ],
    "template": "anagram"
  },
  {
    "list": [
      "Father Aereck",
      "medium",
      "AREA CHEF TREK"
    ],
    "template": "anagram"
  },
  {
    "list": [
      "Father Aereck",
      "medium",
      "AREA CHEF TREK"
    ],
    "template": "anagram"
  },
  {
    "list": [
      "Femi",
      "medium",
      "ME IF"
    ],
    "template": "anagram"
  },
  {
    "list": [
      "Flax Keeper",
      "medium",
      "PEAK REFLEX"
    ],
    "template": "anagram"
  },
  {
    "list": [
      "Fortunato",
      "beginner",
      "TAUNT ROOF"
    ],
    "template": "anagram"
  },
  {
    "list": [
      "Fycie",
      "medium",
      "ICY FE"
    ],
    "template": "anagram"
  },
  {
    "list": [
      "Gabooty",
      "medium",
      "GOT A BOY"
    ],
    "template": "anagram"
  },
  {
    "list": [
      "Gallow",
      "medium",
      "LOW LAG"
    ],
    "template": "anagram"
  },
  {
    "list": [
      "Gertrude",
      "beginner",
      "RUG DETER"
    ],
    "template": "anagram"
  },
  {
    "list": [
      "Gnome Coach",
      "hard",
      "C ON GAME HOC"
    ],
    "template": "anagram"
  },
  {
    "list": [
      "Goreu",
      "master",
      "RUE GO"
    ],
    "template": "anagram"
  },
  {
    "list": [
      "Vemmeldo",
      "elite",
      "LADDER MEMO GUV"
    ],
    "template": "anagram"
  },
  {
    "list": [
      "Guildmaster Lars",
      "master",
      "SLAM DUSTER GRAIL"
    ],
    "template": "anagram"
  },
  {
    "list": [
      "The Hairdresser",
      "beginner",
      "SIR SHARE RED"
    ],
    "template": "anagram"
  },
  {
    "list": [
      "Hickton",
      "medium",
      "THICKNO"
    ],
    "template": "anagram"
  },
  {
    "list": [
      "Horphis",
      "medium",
      "HIS PHOR"
    ],
    "template": "anagram"
  },
  {
    "list": [
      "Immenizz",
      "master",
      "IM N ZEZIM"
    ],
    "template": "anagram"
  },
  {
    "list": [
      "Jaraah",
      "medium",
      "AHA JAR"
    ],
    "template": "anagram"
  },
  {
    "list": [
      "Jethick",
      "medium",
      "HICK JET"
    ],
    "template": "anagram"
  },
  {
    "list": [
      "Karim",
      "medium",
      "R AK MI"
    ],
    "template": "anagram"
  },
  {
    "list": [
      "Kaylee",
      "medium",
      "LEAKEY"
    ],
    "template": "anagram"
  },
  {
    "list": [
      "King Bolren",
      "medium",
      "GOBLIN KERN"
    ],
    "template": "anagram"
  },
  {
    "list": [
      "King Roald",
      "medium",
      "LARK IN DOG"
    ],
    "template": "anagram"
  },
  {
    "list": [
      "Lammy",
      "hard",
      "MY MANGLE LAL"
    ],
    "template": "anagram"
  },
  {
    "list": [
      "Lisse",
      "elite",
      "SNAKES SO I SAIL"
    ],
    "template": "anagram"
  },
  {
    "list": [
      "Lowe",
      "medium",
      "EL OW"
    ],
    "template": "anagram"
  },
  {
    "list": [
      "Lumbridge Guide",
      "hard",
      "BLUE GRIM GUIDED"
    ],
    "template": "anagram"
  },
  {
    "list": [
      "Luminata",
      "master",
      "Mal in Tau"
    ],
    "template": "anagram"
  },
  {
    "list": [
      "Luthas",
      "medium",
      "HALT US"
    ],
    "template": "anagram"
  },
  {
    "list": [
      "Madame Caldarium",
      "medium",
      "CALAMARI MADE MUD"
    ],
    "template": "anagram"
  },
  {
    "list": [
      "Mandrith",
      "elite",
      "DR HITMAN"
    ],
    "template": "anagram"
  },
  {
    "list": [
      "Mandrith",
      "master",
      "DIM THARN"
    ],
    "template": "anagram"
  },
  {
    "list": [
      "Marisi",
      "medium",
      "I AM SIR"
    ],
    "template": "anagram"
  },
  {
    "list": [
      "Martin Thwait",
      "hard",
      "RAT MAT WITHIN"
    ],
    "template": "anagram"
  },
  {
    "list": [
      "Metla",
      "medium",
      "LAME T"
    ],
    "template": "anagram"
  },
  {
    "list": [
      "Tony",
      "master",
      "TWENTY CURE IRON"
    ],
    "template": "anagram"
  },
  {
    "list": [
      "Nicholas",
      "medium",
      "CLASH ION"
    ],
    "template": "anagram"
  },
  {
    "list": [
      "Nieve",
      "medium",
      "I EVEN"
    ],
    "template": "anagram"
  },
  {
    "list": [
      "Nurse Wooned",
      "elite",
      "OUR OWN NEEDS"
    ],
    "template": "anagram"
  },
  {
    "list": [
      "Old Man Ral",
      "master",
      "MOLD LA RAN"
    ],
    "template": "anagram"
  },
  {
    "list": [
      "Old crone",
      "elite",
      "COOL NERD"
    ],
    "template": "anagram"
  },
  {
    "list": [
      "Oneiromancer",
      "elite",
      "CAREER IN MOON"
    ],
    "template": "anagram"
  },
  {
    "list": [
      "Oracle",
      "medium",
      "ARE COL"
    ],
    "template": "anagram"
  },
  {
    "list": [
      "Oronwen",
      "elite",
      "NO OWNER"
    ],
    "template": "anagram"
  },
  {
    "list": [
      "Otto Godblessed",
      "medium",
      "GOBLETS ODD TOES"
    ],
    "template": "anagram"
  },
  {
    "list": [
      "Party Pete",
      "medium",
      "Peaty Pert"
    ],
    "template": "anagram"
  },
  {
    "list": [
      "Primula",
      "master",
      "RIP MAUL"
    ],
    "template": "anagram"
  },
  {
    "list": [
      "Percy",
      "hard",
      "COPPER ORE CRYPTS"
    ],
    "template": "anagram"
  },
  {
    "list": [
      "Radimus Erkle",
      "master",
      "Mus Kil Reader"
    ],
    "template": "anagram"
  },
  {
    "list": [
      "Ranael",
      "beginner",
      "AN EARL"
    ],
    "template": "anagram"
  },
  {
    "list": [
      "Regath",
      "elite",
      "AT HERG"
    ],
    "template": "anagram"
  },
  {
    "list": [
      "Runolf",
      "master",
      "FORLUN"
    ],
    "template": "anagram"
  },
  {
    "list": [
      "Saba",
      "medium",
      "A BAS"
    ],
    "template": "anagram"
  },
  {
    "list": [
      "Sacrifice",
      "master",
      "CAR IF ICES"
    ],
    "template": "anagram"
  },
  {
    "list": [
      "Sigli",
      "elite",
      "Unleash Night Mist"
    ],
    "template": "anagram"
  },
  {
    "list": [
      "Sir Kay",
      "medium",
      "KAY SIR"
    ],
    "template": "anagram"
  },
  {
    "list": [
      "Snowflake",
      "master",
      "A ELF KNOWS"
    ],
    "template": "anagram"
  },
  {
    "list": [
      "The Squire",
      "medium",
      "QUE SIR"
    ],
    "template": "anagram"
  },
  {
    "list": [
      "Steve",
      "medium",
      "VESTE"
    ],
    "template": "anagram"
  },
  {
    "list": [
      "Strange Old Man",
      "hard",
      "DRAGONS LAMENT"
    ],
    "template": "anagram"
  },
  {
    "list": [
      "Taria",
      "medium",
      "Ratai"
    ],
    "template": "anagram"
  },
  {
    "list": [
      "Veronica",
      "beginner",
      "RAIN COVE"
    ],
    "template": "anagram"
  },
  {
    "list": [
      "Wingstone",
      "master",
      "TEN WIGS ON"
    ],
    "template": "anagram"
  },
  {
    "list": [
      "Wise Old Man",
      "hard",
      "Slide Woman"
    ],
    "template": "anagram"
  },
  {
    "list": [
      "Ysgawyn",
      "master",
      "YAWNS GY"
    ],
    "template": "anagram"
  },
  {
    "list": [
      "Zookeeper",
      "medium",
      "EEK ZERO OP"
    ],
    "template": "anagram"
  }
]