[
  {
    "author": "Envision",
    "url": "https://archive.fo/5P5mn",
    "title": "Drop Rates V2",
    "postdate": "14 July 2014",
    "template": "citeforum"
  },
  {
    "author": "Envision",
    "url": "https://archive.fo/5P5mn",
    "title": "Drop Rates V2",
    "name": "drop",
    "postdate": "09 July 2014",
    "template": "citeforum"
  },
  {
    "author": "Envision",
    "url": "https://archive.fo/5P5mn",
    "title": "Drop Rates V2",
    "postdate": "14 July 2014",
    "template": "citeforum"
  },
  {
    "author": "Envision",
    "url": "https://archive.fo/5P5mn",
    "title": "Drop Rates V2",
    "name": "drop",
    "postdate": "09 July 2014",
    "template": "citeforum"
  },
  {
    "author": "Envision",
    "url": "https://archive.fo/5P5mn",
    "title": "Drop Rates V2",
    "name": "drop",
    "postdate": "29 July 2014",
    "template": "citeforum"
  },
  {
    "author": "Envision",
    "url": "https://archive.fo/5P5mn",
    "title": "Drop Rates V2",
    "name": "drop",
    "postdate": "29 July 2014",
    "template": "citeforum"
  },
  {
    "author": "Envision",
    "url": "https://www.reddit.com/r/2007scape/comments/2z71kd/where_can_i_find_clue_scroll_drop_rates/",
    "title": "Drop Rates V2",
    "template": "citeforum"
  },
  {
    "author": "Envision",
    "url": "https://archive.fo/5P5mn",
    "title": "Drop Rates V2",
    "name": "drop",
    "postdate": "29 July 2014",
    "template": "citeforum"
  },
  {
    "url": "http://services.runescape.com/m=forum/forums.ws?14,15,217,65380526",
    "postdate": "27 May 2014",
    "title": "Rules of RuneScape: Update",
    "author": "Mod Pips",
    "archiveurl": "https://web.archive.org/web/20140604161258/http://services.runescape.com/m=forum/forums.ws?14,15,217,65380526",
    "quote": "You may log into multiple accounts across all versions of RuneScape at the same time, however any account you are using must not be involved in any rule breaking or exploitative activity. Any penalties or sanction for such behaviour will be applied to all of your accounts.",
    "template": "citeforum"
  },
  {
    "author": "Mod Archie",
    "url": "http://www.webcitation.org/6lff6fvjI",
    "title": "Ballista/Javelin Stat Changes",
    "forum": "Old School Announcements",
    "postdate": "31 October 2016",
    "template": "citeforum"
  },
  {
    "author": "Mod Ed",
    "url": "http://services.runescape.com/m=forum/forums.ws?380,381,397,65924240,goto,4",
    "title": "Mining Guild Expansion",
    "archiveurl": "https://archive.is/6BqBZ",
    "archivedate": "15:02, 20 May 2021 (UTC)",
    "forum": "Old School Announcements",
    "postdate": "22 June 2017",
    "template": "citeforum"
  },
  {
    "author": "Mod Ed",
    "url": "http://services.runescape.com/m=forum/forums.ws?380,381,397,65924240,goto,4",
    "title": "Mining Guild Expansion",
    "archiveurl": "https://archive.is/6BqBZ",
    "archivedate": "15:02, 20 May 2021 (UTC)",
    "forum": "Old School Announcements",
    "postdate": "22 June 2017",
    "template": "citeforum"
  },
  {
    "author": "Mod Ronan",
    "url": "http://services.runescape.com/m=forum/forums.ws?380,381,270,65755317",
    "title": "Dev Blog: Monkey Madness II",
    "postdate": "22 February 2016",
    "archiveurl": "https://archive.is/kHlol",
    "archivedate": "16 July 2020",
    "forum": "Old School Announcements",
    "template": "citeforum"
  },
  {
    "author": "Mod John C",
    "url": "http://www.webcitation.org/6Qo8EiqEo",
    "title": "Dev blog: Rewarding Rewards",
    "forum": "Old School RuneScape General",
    "postdate": "06-Jun-2014",
    "template": "citeforum"
  },
  {
    "author": "Mod Wolf",
    "url": "https://archive.fo/X9ifv",
    "title": "Poll 67 Updates and Hosidius Improvements",
    "forum": "Reddit",
    "postdate": "30 May 2019",
    "template": "citeforum"
  },
  {
    "author": "Mod Ronan",
    "url": "http://services.runescape.com/m=forum/forums.ws?380,381,327,65834508",
    "title": "Dev Blog: Ourania Altar",
    "forum": "Old School Announcements",
    "postdate": "21 September 2016",
    "archiveurl": "https://archive.is/e03ZN",
    "archivedate": "16 July 2020",
    "template": "citeforum"
  },
  {
    "author": "Envision",
    "url": "https://archive.fo/5P5mn",
    "title": "Drop Rates V2",
    "postdate": "29 July 2014",
    "name": "drop",
    "template": "citeforum"
  },
  {
    "author": "Envision",
    "url": "https://archive.fo/5P5mn",
    "title": "Drop Rates V2",
    "postdate": "29 July 2014",
    "template": "citeforum"
  },
  {
    "author": "Envision",
    "url": "https://archive.fo/5P5mn",
    "title": "Drop Rates V2",
    "postdate": "29 July 2014",
    "name": "DV2",
    "template": "citeforum"
  },
  {
    "author": "Envision",
    "url": "https://archive.fo/5P5mn",
    "title": "Drop Rates V2",
    "postdate": "29 July 2014",
    "name": "DV2",
    "template": "citeforum"
  },
  {
    "author": "Envision",
    "postdate": "29 July 2014",
    "url": "https://archive.fo/5P5mn",
    "title": "Drop Rates V2",
    "name": "Drop Rates V2",
    "template": "citeforum"
  },
  {
    "author": "Mod Wolf",
    "url": "https://archive.fo/X9ifv",
    "title": "Poll 67 Updates and Hosidius Improvements",
    "forum": "Reddit",
    "postdate": "30 May 2019",
    "template": "citeforum"
  },
  {
    "author": "Mod Paul",
    "url": "http://www.webcitation.org/62mt28ws6",
    "title": "Relief for Bots? WTF JAGEX!",
    "forum": "RuneScape",
    "postdate": "30 September 2010",
    "template": "citeforum"
  },
  {
    "author": "Envision",
    "url": "https://archive.fo/5P5mn",
    "title": "Drop Rates V2",
    "name": "Drop Rates V2",
    "postdate": "14 July 2014",
    "template": "citeforum"
  },
  {
    "author": "Mod Archie",
    "url": "http://www.webcitation.org/6lff6fvjI",
    "title": "Ballista/Javelin Stat Changes",
    "forum": "Old School Announcements",
    "postdate": "October 31, 2016",
    "template": "citeforum"
  },
  {
    "author": "Mod West",
    "url": "https://www.reddit.com/r/2007scape/comments/67wfpd/chasm_of_fire_easter_egg_osbuddy_map_floor_0/dgts9y1/",
    "title": "Chasm of Fire easter egg (OSBuddy map floor 0)",
    "forum": "Reddit",
    "postdate": "April 27, 2017",
    "template": "citeforum"
  },
  {
    "author": "Mod Ed",
    "url": "http://services.runescape.com/m=forum/forums.ws?380,381,397,65924240,goto,4",
    "title": "Mining Guild Expansion",
    "archiveurl": "https://archive.is/6BqBZ",
    "archivedate": "15:02, 20 May 2021 (UTC)",
    "forum": "Old School Announcements",
    "postdate": "22 June 2017",
    "template": "citeforum"
  },
  {
    "author": "Envision",
    "url": "https://archive.fo/5P5mn",
    "postdate": "29 July 2014",
    "title": "Drop Rates V2",
    "name": "DV2",
    "template": "citeforum"
  },
  {
    "author": "Mod Ronan",
    "url": "http://services.runescape.com/m=forum/forums.ws?380,381,129,65525537",
    "title": "Integrity Survey Followup",
    "postdate": "27 November 2014",
    "archiveurl": "https://archive.is/WCPI6",
    "archivedate": "16 July 2020",
    "quote": "As such from now we will be considering anyone being part of a commission staking friends chat (that is hosting, participating and advertising) as involved in real world trading. In effect, commission staking is now against the rules.",
    "name": "Commission Staking",
    "template": "citeforum"
  },
  {
    "author": "Mod Ronan",
    "url": "http://services.runescape.com/m=forum/forums.ws?380,381,129,65525537",
    "title": "Integrity Survey Followup",
    "postdate": "27 November 2014",
    "archiveurl": "https://archive.is/q2gjW",
    "archivedate": "16 July 2020",
    "quote": "Off the back of this, we have redesigned the report abuse screen to include a new option to report other players that are harassing you.",
    "name": "Player Harassment",
    "template": "citeforum"
  },
  {
    "author": "Mod Sween",
    "url": "http://services.runescape.com/m=news/old-school-runescape-status-update?oldschool=1",
    "title": "Old School RuneScape Status Update",
    "forum": "Old School RuneScape",
    "postdate": "12 July 2018",
    "template": "citeforum"
  },
  {
    "author": "Mod Wolf",
    "url": "https://archive.fo/X9ifv",
    "title": "Poll 67 Updates and Hosidius Improvements",
    "forum": "Reddit",
    "postdate": "30 May 2019",
    "template": "citeforum"
  },
  {
    "author": "Bitterkoekje",
    "url": "https://web.archive.org/web/20190905124128/http://webcache.googleusercontent.com/search?q=cache:http://services.runescape.com/m=forum/forums.ws?317,318,712,65587452",
    "title": "Combat Formulas",
    "postdate": "10 March 2015",
    "name": "Bitterkoekje",
    "template": "citeforum"
  },
  {
    "author": "Envision",
    "url": "https://archive.fo/5P5mn",
    "archivedate": "29 Mar 2019",
    "title": "Drop Rates V2",
    "name": "Drop Rates V2",
    "template": "citeforum"
  },
  {
    "author": "Mod Mat K",
    "url": "https://www.reddit.com/r/2007scape/comments/35u038/legitimately_unsure_how_the_cow_got_into_nmz/cr86r9q/",
    "title": "Legitimately unsure how the Cow got into NMZ?",
    "forum": "Reddit",
    "postdate": "13 May 2015",
    "accessdate": "11:43, August 23, 2017 (UTC)",
    "template": "citeforum"
  },
  {
    "author": "Envision",
    "url": "http://forum.runescape.com/forums.ws?317,318,288,65354165",
    "archiveurl": "https://archive.fo/5P5mn",
    "postdate": "22 April 2014",
    "archivedate": "4 Aug 2014",
    "title": "Drop Rates V2",
    "template": "citeforum"
  },
  {
    "author": "Envision",
    "url": "https://archive.fo/5P5mn",
    "title": "Drop Rates V2",
    "postdate": "29 July 2014",
    "template": "citeforum"
  },
  {
    "author": "Envision",
    "url": "https://archive.fo/5P5mn",
    "title": "Drop Rates V2",
    "name": "Drop Rates V2",
    "template": "citeforum"
  },
  {
    "author": "Envision",
    "url": "https://archive.fo/5P5mn",
    "title": "Drop Rates V2",
    "name": "Drop Rates V2",
    "template": "citeforum"
  },
  {
    "author": "Envision",
    "url": "https://archive.fo/5P5mn",
    "title": "Drop Rates V2",
    "name": "Drop Rates V2",
    "template": "citeforum"
  },
  {
    "author": "Bitterkoekje",
    "url": "https://web.archive.org/web/20190905124128/http://webcache.googleusercontent.com/search?q=cache:http://services.runescape.com/m=forum/forums.ws?317,318,712,65587452",
    "title": "Combat Formulas",
    "postdate": "10 March 2015",
    "name": "Bitterkoekje",
    "template": "citeforum"
  },
  {
    "author": "Mod Ronan",
    "url": "http://services.runescape.com/m=news/architectural-alliance?oldschool=1",
    "title": "Architectural Alliance",
    "forum": "Old School RuneScape",
    "postdate": "March 3, 2016",
    "template": "citeforum"
  },
  {
    "author": "Mod Wolf",
    "url": "https://archive.fo/X9ifv",
    "title": "Poll 67 Updates and Hosidius Improvements",
    "forum": "Reddit",
    "postdate": "30 May 2019",
    "template": "citeforum"
  },
  {
    "author": "Mod Mark",
    "url": "http://www.webcitation.org/5m7lGdGD1",
    "title": "Answers from RS Content",
    "forum": "News & Announcements",
    "postdate": "10 September 2009",
    "template": "citeforum"
  },
  {
    "author": "Bitterkoekje",
    "url": "https://web.archive.org/web/20190905124128/http://webcache.googleusercontent.com/search?q=cache:http://services.runescape.com/m=forum/forums.ws?317,318,712,65587452,goto,2",
    "title": "Combat Formulas",
    "postdate": "10 March 2015",
    "name": "Bitterkoekje",
    "template": "citeforum"
  },
  {
    "author": "Bitterkoekje",
    "url": "https://web.archive.org/web/20190905124128/http://webcache.googleusercontent.com/search?q=cache:http://services.runescape.com/m=forum/forums.ws?317,318,712,65587452,goto,2",
    "title": "Combat Formulas",
    "postdate": "10 March 2015",
    "name": "Bitterkoekje",
    "template": "citeforum"
  },
  {
    "author": "Mod Archie",
    "url": "http://www.webcitation.org/6lff6fvjI",
    "title": "Ballista/Javelin Stat Changes",
    "forum": "Old School Announcements",
    "postdate": "October 31, 2016",
    "template": "citeforum"
  },
  {
    "author": "Bitterkoekje",
    "url": "https://web.archive.org/web/20190905124128/http://webcache.googleusercontent.com/search?q=cache:http://services.runescape.com/m=forum/forums.ws?317,318,712,65587452",
    "title": "Combat Formulas",
    "postdate": "10 March 2015",
    "name": "Bitterkoekje",
    "template": "citeforum"
  },
  {
    "author": "Bitterkoekje",
    "url": "https://web.archive.org/web/20190905124128/http://webcache.googleusercontent.com/search?q=cache:http://services.runescape.com/m=forum/forums.ws?317,318,712,65587452",
    "title": "Combat Formulas",
    "postdate": "10 March 2015",
    "name": "Bitterkoekje",
    "template": "citeforum"
  },
  {
    "author": "Envision",
    "url": "https://archive.fo/5P5mn",
    "title": "Drop Rates V2",
    "name": "Drop Rates V2",
    "template": "citeforum"
  },
  {
    "author": "Envision",
    "url": "https://archive.fo/5P5mn",
    "title": "Drop Rates V2",
    "name": "Drop Rates V2",
    "template": "citeforum"
  },
  {
    "url": "https://services.runescape.com/m=forum/forums.ws?380,381,169,65611402",
    "archiveurl": "https://archive.is/XgmHi",
    "author": "Mod Ronan",
    "title": "Crystal Halberd Special & More",
    "postdate": "23 April 2015",
    "archivedate": "28 August 2021",
    "template": "citeforum"
  },
  {
    "title": "Gods ~ their Races and Species",
    "author": "Mod John A",
    "forum": "RuneScape Lore Discussion",
    "postdate": "7 August 2013",
    "url": "http://www.webcitation.org/6IiYPdVYA",
    "name": "johna2",
    "template": "citeforum"
  },
  {
    "author": "Mod Stevew",
    "url": "http://www.webcitation.org/5o4OLXX5h",
    "title": "Live Q&A with CM - Answers",
    "postdate": "4 March 2010",
    "template": "citeforum"
  },
  {
    "author": "Mod Timbo",
    "url": "http://www.webcitation.org/5o4OjVaok",
    "title": "Live Q&A with CM - Answers",
    "postdate": "4 March 2010",
    "template": "citeforum"
  },
  {
    "author": "MrsWetlander",
    "url": "http://archive.is/Nl2Rh",
    "title": "A Four Letter Word",
    "postdate": "17 March 2016",
    "template": "citeforum"
  },
  {
    "author": "MBBrabus",
    "url": "https://old.reddit.com/r/2007scape/comments/8iex60/loot_from_9790_herbiboar_harvests_with_xp_tables/",
    "title": "LOOT FROM 9790 HERBIBOAR HARVESTS (WITH XP TABLES)",
    "forum": "Reddit",
    "postdate": "10 May 2018",
    "name": "Reddit",
    "template": "citeforum"
  },
  {
    "author": "Envision",
    "url": "https://archive.fo/5P5mn",
    "title": "Drop Rates V2",
    "postdate": "29 July 2014",
    "name": "drop",
    "template": "citeforum"
  },
  {
    "author": "Envision",
    "url": "https://archive.fo/5P5mn",
    "title": "Drop Rates V2",
    "name": "Drop Rates V2",
    "template": "citeforum"
  },
  {
    "author": "Mod Wolf",
    "url": "https://archive.fo/X9ifv",
    "title": "Poll 67 Updates and Hosidius Improvements",
    "forum": "Reddit",
    "postdate": "30 May 2019",
    "template": "citeforum"
  },
  {
    "author": "Mod West",
    "url": "https://www.reddit.com/r/2007scape/comments/5df4de/some_westerner/da422t5/",
    "title": "Some Westerner",
    "forum": "Reddit",
    "postdate": "17 November 2016",
    "template": "citeforum"
  },
  {
    "author": "Mod West",
    "url": "https://www.reddit.com/r/2007scape/comments/7aj7e7/please_read_updated_mage_arena_ii_cape_idea/dpaff08/",
    "title": "please read: Updated Mage Arena II Cape Idea",
    "forum": "Reddit",
    "postdate": "3 November 2017",
    "template": "citeforum"
  },
  {
    "author": "acy2fast",
    "url": "https://www.reddit.com/r/2007scape/comments/7p8xcb/thanks_to_the_jmods_for_these_amazing_gifts_from/dsgityy/",
    "title": "Thanks to the Jmods for these amazing gifts from my work on the Mage Arena II capes!! The coasters, poster, and varrock mouse pad were great, but gotta show love for the God Ash-signed osrs mug?!",
    "forum": "Reddit",
    "postdate": "9 January 2018",
    "template": "citeforum"
  },
  {
    "author": "Mod West",
    "url": "https://www.reddit.com/r/2007scape/comments/7aj7e7/please_read_updated_mage_arena_ii_cape_idea/dpaff08/",
    "title": "please read: Updated Mage Arena II Cape Idea",
    "forum": "Reddit",
    "postdate": "3 November 2017",
    "template": "citeforum"
  },
  {
    "author": "acy2fast",
    "url": "https://www.reddit.com/r/2007scape/comments/7p8xcb/thanks_to_the_jmods_for_these_amazing_gifts_from/dsgityy/",
    "title": "Thanks to the Jmods for these amazing gifts from my work on the Mage Arena II capes!! The coasters, poster, and varrock mouse pad were great, but gotta show love for the God Ash-signed osrs mug?!",
    "forum": "Reddit",
    "postdate": "9 January 2018",
    "template": "citeforum"
  },
  {
    "author": "Mod West",
    "url": "https://www.reddit.com/r/2007scape/comments/7aj7e7/please_read_updated_mage_arena_ii_cape_idea/dpaff08/",
    "title": "please read: Updated Mage Arena II Cape Idea",
    "forum": "Reddit",
    "postdate": "3 November 2017",
    "template": "citeforum"
  },
  {
    "author": "acy2fast",
    "url": "https://www.reddit.com/r/2007scape/comments/7p8xcb/thanks_to_the_jmods_for_these_amazing_gifts_from/dsgityy/",
    "title": "Thanks to the Jmods for these amazing gifts from my work on the Mage Arena II capes!! The coasters, poster, and varrock mouse pad were great, but gotta show love for the God Ash-signed osrs mug?!",
    "forum": "Reddit",
    "postdate": "9 January 2018",
    "template": "citeforum"
  },
  {
    "author": "Envision",
    "url": "https://archive.fo/5P5mn",
    "title": "Drop Rates V2",
    "postdate": "29 July 2014",
    "name": "Drop Rates V2",
    "template": "citeforum"
  },
  {
    "author": "Mod Ronan",
    "url": "http://services.runescape.com/m=news/the-inferno?oldschool=1",
    "title": "The Inferno",
    "forum": "Old School RuneScape",
    "postdate": "June 1, 2017",
    "template": "citeforum"
  },
  {
    "author": "Mod Ronan",
    "url": "https://secure.runescape.com/m=forum/sl=0/forums?380,381,98,65479193",
    "title": "Dev Blog: Content Poll #25",
    "forum": "Old School Announcements",
    "postdate": "15 September 2014",
    "archiveurl": "https://archive.is/TbV0g",
    "archivedate": "15 September 2020",
    "template": "citeforum"
  },
  {
    "author": "Mod Archie",
    "url": "http://www.webcitation.org/6lff6fvjI",
    "title": "Ballista/Javelin Stat Changes",
    "forum": "Old School Announcements",
    "postdate": "October 31, 2016",
    "template": "citeforum"
  },
  {
    "author": "Mod Ed",
    "url": "http://services.runescape.com/m=forum/forums.ws?380,381,397,65924240,goto,4",
    "title": "Mining Guild Expansion",
    "archiveurl": "https://archive.is/6BqBZ",
    "archivedate": "15:02, 20 May 2021 (UTC)",
    "forum": "Old School Announcements",
    "postdate": "22 June 2017",
    "template": "citeforum"
  },
  {
    "author": "Mod Balance",
    "url": "http://services.runescape.com/m=forum/forums.ws?14,15,372,65813215",
    "archiveurl": "http://archive.is/Y7wIt",
    "archivedate": "14 July 2016",
    "title": "Jagex Investment & Aquisition",
    "forum": "General",
    "postdate": "14 July 2016",
    "template": "citeforum"
  },
  {
    "author": "Envision",
    "url": "https://archive.fo/5P5mn",
    "title": "Drop Rates V2",
    "postdate": "29 July 2014",
    "name": "drop",
    "template": "citeforum"
  },
  {
    "author": "Envision",
    "url": "https://archive.fo/5P5mn",
    "title": "Drop Rates V2",
    "name": "Drop Rates V2",
    "template": "citeforum"
  },
  {
    "author": "Envision",
    "url": "https://archive.fo/5P5mn",
    "title": "Drop Rates V2",
    "name": "'Drop Rates V2'",
    "template": "citeforum"
  },
  {
    "author": "rururupert",
    "url": "https://www.reddit.com/r/2007scape/comments/fmcf2k/suggestion_give_us_monkey_backpacks_to_grind_for/",
    "title": "Suggestion: Give us monkey backpacks to grind for while in quarantine",
    "forum": "Reddit",
    "postdate": "21 March 2020",
    "template": "citeforum"
  },
  {
    "author": "589776",
    "url": "http://forum.runescape.com/lang/en/aff/runescape/forums.ws?16,17,900,30594780",
    "forum": "Future Updates",
    "postdate": "5 September 2006",
    "title": "~ Future Update News #16 ~",
    "notes": "\"Upstairs in the mining consortium a minigame symbol has appeared and been removed, however Mod Greg said he will, in the future, make a minigame here.\"",
    "archiveurl": "https://web.archive.org/web/20061102143824/http://forum.runescape.com/lang/en/aff/runescape/forums.ws?16,17,900,30594780",
    "template": "citeforum"
  },
  {
    "author": "Envision",
    "url": "https://archive.fo/5P5mn",
    "title": "Drop Rates V2",
    "postdate": "29 July 2014",
    "name": "DV2",
    "template": "citeforum"
  },
  {
    "author": "Mod Ronan",
    "url": "https://secure.runescape.com/m=forum/forums?380,381,345,65849743",
    "archiveurl": "https://archive.ph/SN2r3",
    "title": "Hardcore Ironman Mode",
    "forum": "Old School Announcements",
    "postdate": "10 November 2016",
    "archivedate": "16 Jan 2022",
    "template": "citeforum"
  },
  {
    "author": "Envision",
    "url": "https://archive.fo/5P5mn",
    "title": "Drop Rates V2",
    "name": "Drop Rates V2",
    "template": "citeforum"
  },
  {
    "author": "rururupert",
    "url": "https://www.reddit.com/r/2007scape/comments/fmcf2k/suggestion_give_us_monkey_backpacks_to_grind_for/",
    "title": "Suggestion: Give us monkey backpacks to grind for while in quarantine",
    "forum": "Reddit",
    "postdate": "21 March 2020",
    "template": "citeforum"
  },
  {
    "author": "Envision",
    "url": "https://archive.fo/5P5mn",
    "title": "Drop Rates V2",
    "postdate": "29 July 2014",
    "name": "DV2",
    "template": "citeforum"
  },
  {
    "author": "Bitterkoekje",
    "url": "https://web.archive.org/web/20190905124128/http://webcache.googleusercontent.com/search?q=cache:http://services.runescape.com/m=forum/forums.ws?317,318,712,65587452",
    "title": "Combat Formulas",
    "postdate": "10 March 2015",
    "name": "Bitterkoekje",
    "template": "citeforum"
  },
  {
    "url": "http://services.runescape.com/m=forum/forums.ws?14,15,217,65380526",
    "postdate": "27 May 2014",
    "title": "Rules of RuneScape: Update",
    "author": "Mod Pips",
    "template": "citeforum"
  },
  {
    "author": "rururupert",
    "url": "https://www.reddit.com/r/2007scape/comments/fmcf2k/suggestion_give_us_monkey_backpacks_to_grind_for/",
    "title": "Suggestion: Give us monkey backpacks to grind for while in quarantine",
    "forum": "Reddit",
    "postdate": "21 March 2020",
    "template": "citeforum"
  },
  {
    "author": "Mod Archie",
    "url": "http://www.webcitation.org/6lff6fvjI",
    "title": "Ballista/Javelin Stat Changes",
    "forum": "Old School Announcements",
    "postdate": "October 31, 2016",
    "template": "citeforum"
  },
  {
    "author": "Mod Ed",
    "url": "http://services.runescape.com/m=forum/forums.ws?380,381,397,65924240,goto,4",
    "title": "Mining Guild Expansion",
    "archiveurl": "https://archive.is/6BqBZ",
    "archivedate": "15:02, 20 May 2021 (UTC)",
    "forum": "Old School Announcements",
    "postdate": "22 June 2017",
    "template": "citeforum"
  },
  {
    "author": "Mod Meadows",
    "url": "https://archive.ph/ZdRCP",
    "title": "2010 Dungeoneering Developers' Blog",
    "forum": "Reddit",
    "postdate": "10 June 2019",
    "accessdate": "20 January 2020",
    "template": "citeforum"
  },
  {
    "author": "Mod Shauny",
    "url": "https://archive.is/LtjbF",
    "title": "Meet the Ninjas!",
    "forum": "Ninja Team",
    "postdate": "12 July 2017",
    "name": "Ninja",
    "template": "citeforum"
  },
  {
    "author": "Mod Ash",
    "name": "uppervslower",
    "url": "http://services.runescape.com/m=forum/forums.ws?380,381,366,65884485,goto,2#18",
    "archiveurl": "https://archive.is/JgXHN#70%",
    "title": "Shift-Click Drop & QoL",
    "forum": "Old School Announcements",
    "postdate": "23-Feb-2017 11:09:04",
    "archivedate": "28 August 2021",
    "template": "citeforum"
  },
  {
    "author": "Mod Ash",
    "url": "http://services.runescape.com/m=forum/forums.ws?380,381,369,65889334,goto,5#44",
    "title": "General QoL!",
    "archiveurl": "https://archive.is/b8ZtL#40%",
    "forum": "Old School Announcements",
    "postdate": "09-Mar-2017 13:06:57",
    "archivedate": "28 August 2021",
    "template": "citeforum"
  },
  {
    "author": "Mod Ac",
    "url": "http://www.webcitation.org/5oBrPKmjt",
    "title": "Mouse keys - Rule Clarity.",
    "postdate": "4 March 2010",
    "template": "citeforum"
  },
  {
    "author": "Mod Ronan",
    "url": "http://services.runescape.com/m=forum/forums.ws?380,381,270,65755317",
    "archiveurl": "https://archive.is/XMwqI",
    "title": "Dev Blog: Monkey Madness II",
    "postdate": "22 February 2016",
    "archivedate": "28 August 2021",
    "template": "citeforum"
  },
  {
    "author": "Mod Mat K",
    "url": "https://www.reddit.com/r/2007scape/comments/35u038/legitimately_unsure_how_the_cow_got_into_nmz/cr86r9q/",
    "title": "Legitimately unsure how the Cow got into NMZ?",
    "forum": "Reddit",
    "postdate": "13 May 2015",
    "template": "citeforum"
  },
  {
    "author": "Envision",
    "url": "https://archive.fo/5P5mn",
    "title": "Drop Rates V2",
    "postdate": "29 July 2014",
    "name": "DV2",
    "template": "citeforum"
  },
  {
    "author": "Mod Pips",
    "title": "Old School here to stay!",
    "url": "http://services.runescape.com/m=forum/forums.ws?380,381,76,65448270",
    "postdate": "7 June 2013",
    "accessdate": "10:21, May 8, 2017 (UTC)",
    "name": "OSRS Stay",
    "template": "citeforum"
  },
  {
    "author": "Mod Sween",
    "url": "http://services.runescape.com/m=forum/forums.ws?317,318,456,65932067",
    "title": "Old School Mobile FAQ",
    "forum": "Old School RuneScape General",
    "postdate": "17 July 2017",
    "accessdate": "17 July 2017",
    "archiveurl": "https://archive.fo/cKsSC",
    "archivedate": "17 July 2017",
    "template": "citeforum"
  },
  {
    "author": "Mod Ash",
    "url": "http://services.runescape.com/m=forum/forums.ws?380,381,366,65884485,goto,2#18",
    "title": "Shift-Click Drop & QoL",
    "forum": "Old School Announcements",
    "postdate": "23-Feb-2017 11:09:04",
    "archiveurl": "https://archive.ph/WqHuH",
    "archivedate": "15 February 2024",
    "template": "citeforum"
  },
  {
    "author": "Mod Ash",
    "url": "http://services.runescape.com/m=forum/forums.ws?380,381,369,65889334,goto,5#44",
    "title": "General QoL!",
    "forum": "Old School Announcements",
    "postdate": "09-Mar-2017 13:06:57",
    "archiveurl": "https://archive.ph/sCI2z",
    "archivedate": "15 February 2024",
    "template": "citeforum"
  },
  {
    "author": "Mod Andrew",
    "url": "http://www.webcitation.org/5tAFwyG3g",
    "title": "Answers from Andrew - Q&A!",
    "forum": "News & Announcements",
    "postdate": "3 September 2009",
    "template": "citeforum"
  },
  {
    "author": "rururupert",
    "url": "https://www.reddit.com/r/2007scape/comments/fmcf2k/suggestion_give_us_monkey_backpacks_to_grind_for/",
    "title": "Suggestion: Give us monkey backpacks to grind for while in quarantine",
    "forum": "Reddit",
    "postdate": "21 March 2020",
    "template": "citeforum"
  },
  {
    "title": "Gods ~ their Races and Species",
    "author": "Mod John A",
    "forum": "RuneScape Lore Discussion",
    "postdate": "7 August 2013",
    "url": "http://www.webcitation.org/6IiYPdVYA",
    "name": "johna2",
    "template": "citeforum"
  },
  {
    "author": "Mod Emilee",
    "url": "http://www.webcitation.org/5zV9bHzDw",
    "title": "Ornate Katana Specific FAQ",
    "forum": "Recent Updates",
    "postdate": "15 June 2011",
    "template": "citeforum"
  },
  {
    "author": "Mod Mat K",
    "url": "http://www.webcitation.org/61DSpF7U7",
    "title": "MMG's Friends Chat Channel",
    "forum": "Community Home",
    "postdate": "23 August 2011",
    "template": "citeforum"
  },
  {
    "author": "Mod Wolf",
    "url": "https://archive.fo/X9ifv",
    "title": "Poll 67 Updates and Hosidius Improvements",
    "forum": "Reddit",
    "postdate": "30 May 2019",
    "template": "citeforum"
  },
  {
    "author": "Mod Ronan",
    "url": "http://services.runescape.com/m=forum/forums.ws?380,381,270,65755317",
    "archiveurl": "https://archive.is/XMwqI",
    "title": "Dev Blog: Monkey Madness II",
    "postdate": "22 February 2016",
    "archivedate": "28 August 2021",
    "forum": "RuneScape Forums",
    "template": "citeforum"
  },
  {
    "author": "Mod Chris E",
    "url": "http://www.webcitation.org/67dLb5cTa",
    "title": "Game Engine Answers!",
    "postdate": "13 April 2012",
    "template": "citeforum"
  },
  {
    "author": "Mod Archie",
    "url": "http://www.webcitation.org/6lff6fvjI",
    "title": "Ballista/Javelin Stat Changes",
    "forum": "Old School Announcements",
    "postdate": "October 31, 2016",
    "template": "citeforum"
  },
  {
    "author": "Mod Ed",
    "url": "http://services.runescape.com/m=forum/forums.ws?380,381,397,65924240,goto,4",
    "title": "Mining Guild Expansion",
    "archiveurl": "https://archive.is/6BqBZ",
    "archivedate": "15:02, 20 May 2021 (UTC)",
    "forum": "Old School Announcements",
    "postdate": "22 June 2017",
    "template": "citeforum"
  },
  {
    "author": "Mod Ronan",
    "url": "http://services.runescape.com/m=forum/forums.ws?380,381,217,65675810",
    "archiveurl": "https://archive.is/rUZqi",
    "title": "DevBlog: Sailing - An Overview",
    "forum": "Old School RuneScape",
    "postdate": "September 9, 2015",
    "archivedate": "28 August 2021",
    "name": "DB",
    "template": "citeforum"
  },
  {
    "author": "FoxcRS",
    "url": "https://www.reddit.com/r/2007scape/comments/n0ot3m/suggestion_reconsider_tob_hard_mode_rewards/",
    "title": "Suggestion: Reconsider ToB Hard Mode Rewards",
    "forum": "Reddit",
    "postdate": "28 April 2021",
    "template": "citeforum"
  },
  {
    "author": "Envision",
    "url": "https://archive.fo/5P5mn",
    "title": "Drop Rates V2",
    "name": "\"Drop Rates V2\"",
    "template": "citeforum"
  },
  {
    "author": "Envision",
    "url": "https://archive.fo/5P5mn",
    "title": "Drop Rates V2",
    "name": "Drop Rates V2",
    "template": "citeforum"
  },
  {
    "author": "Envision",
    "url": "https://archive.fo/5P5mn",
    "title": "Drop Rates V2",
    "name": "Drop Rates V2",
    "template": "citeforum"
  },
  {
    "author": "rururupert",
    "url": "https://www.reddit.com/r/2007scape/comments/fmcf2k/suggestion_give_us_monkey_backpacks_to_grind_for/",
    "title": "Suggestion: Give us monkey backpacks to grind for while in quarantine",
    "forum": "Reddit",
    "postdate": "21 March 2020",
    "template": "citeforum"
  },
  {
    "author": "Envision",
    "url": "https://archive.fo/5P5mn",
    "title": "Drop Rates V2",
    "name": "DV2",
    "template": "citeforum"
  },
  {
    "author": "moronijess",
    "url": "https://www.reddit.com/r/2007scape/comments/117fp21/sandbreaker_axe_concept_for_community_design/",
    "title": "Sandbreaker Axe Concept for Community Design",
    "forum": "Reddit",
    "postdate": "20 February 2023",
    "template": "citeforum"
  },
  {
    "author": "Mod Archie",
    "url": "http://www.webcitation.org/6lff6fvjI",
    "title": "Ballista/Javelin Stat Changes",
    "forum": "Old School Announcements",
    "postdate": "October 31, 2016",
    "template": "citeforum"
  },
  {
    "author": "Envision",
    "url": "https://archive.fo/5P5mn",
    "title": "Drop Rates V2",
    "template": "citeforum"
  },
  {
    "author": "Envision",
    "url": "https://archive.fo/5P5mn",
    "title": "Drop Rates V2",
    "postdate": "29 July 2014",
    "name": "DV2",
    "template": "citeforum"
  },
  {
    "author": "33Lemon",
    "url": "https://www.reddit.com/r/2007scape/comments/nprwuw/suggestion_equipment_rebalance_tool_store_5",
    "title": "[Suggestion] Equipment Rebalance: Tool store 5",
    "forum": "Reddit",
    "postdate": "1 June 2021",
    "template": "citeforum"
  },
  {
    "author": "Mod Ronan",
    "url": "http://services.runescape.com/m=forum/forums.ws?380,381,270,65755317",
    "archiveurl": "https://archive.is/XMwqI",
    "title": "Dev Blog: Monkey Madness II",
    "postdate": "22 February 2016",
    "archivedate": "28 August 2021",
    "forum": "RuneScape Forums",
    "template": "citeforum"
  },
  {
    "author": "Mod Husky",
    "url": "http://archive.fo/edpK3",
    "title": "Mod Husky - Forthos Dungeon FAQ",
    "forum": "Reddit",
    "postdate": "8 July 2019",
    "template": "citeforum"
  },
  {
    "author": "Envision",
    "url": "https://archive.fo/5P5mn",
    "title": "Drop Rates V2",
    "name": "DV2",
    "template": "citeforum"
  },
  {
    "author": "Mod Ed",
    "url": "http://services.runescape.com/m=forum/forums.ws?380,381,397,65924240,goto,4",
    "archiveurl": "https://archive.ph/tNJJY",
    "archivedate": "28 March 2022",
    "title": "Mining Guild Expansion",
    "forum": "Old School Announcements",
    "postdate": "22 June 2017",
    "template": "citeforum"
  },
  {
    "author": "Envision",
    "url": "https://archive.fo/5P5mn",
    "title": "Drop Rates V2",
    "postdate": "29 July 2014",
    "name": "drop",
    "template": "citeforum"
  },
  {
    "author": "Mod Wolf",
    "url": "https://archive.fo/X9ifv",
    "title": "Poll 67 Updates and Hosidius Improvements",
    "forum": "Reddit",
    "postdate": "30 May 2019",
    "template": "citeforum"
  },
  {
    "author": "Mod John A",
    "url": "http://www.webcitation.org/6ItJhi0qc",
    "title": "Gods ~ their Races and Species",
    "forum": "RuneScape Lore Discussion",
    "postdate": "13 August 2013",
    "template": "citeforum"
  }
]