[
  {
    "north": "Mount Karuulm",
    "west": "Farming Guild",
    "location": "Battlefront",
    "east": "Lizardman Canyon",
    "south": "Lake Molch",
    "template": "relative location"
  },
  {
    "location": "Baxtorian Falls",
    "north": "Otto's Grotto",
    "west": "Tree Gnome Stronghold",
    "south": "West Ardougne",
    "east": "Coal Trucks",
    "template": "relative location"
  },
  {
    "location": "Burgh de Rott",
    "north": "Mort'ton",
    "east": "Meiyerditch",
    "south": "Ruins of Uzer",
    "west": "Abandoned Mine",
    "template": "relative location"
  },
  {
    "location": "Camelot",
    "north": "Sinclair Mansion",
    "west": "Seers' Village",
    "south": "Keep Le Faye",
    "east": "White Wolf Mountain",
    "template": "relative location"
  },
  {
    "location": "Canifis",
    "north": "Slayer Tower",
    "east": "Haunted Woods",
    "south": "Mort Myre Swamp",
    "west": "Paterdomus",
    "template": "relative location"
  },
  {
    "location": "Canifis Hunter area",
    "north": "Fenkenstrain's Castle",
    "south": "The Hollows",
    "east": "Port Phasmatys",
    "west": "Mort Myre Swamp",
    "template": "relative location"
  },
  {
    "location": "Castle Wars",
    "north": "Observatory",
    "west": "Lletya",
    "south": "Jiggig",
    "east": "Yanille",
    "template": "relative location"
  },
  {
    "location": "Chaos Temple (Wilderness)",
    "north": "Bone Yard",
    "west": "Ferox Enclave",
    "south": "Varrock Palace",
    "east": "Slayer Tower",
    "template": "relative location"
  },
  {
    "north": "Grand Exchange",
    "west": "Barbarian Village",
    "location": "Cooks' Guild",
    "east": "Varrock",
    "south": "Champions' Guild",
    "template": "relative location"
  },
  {
    "location": "Dark Warriors' Fortress",
    "north": "Bandit Camp (Wilderness)",
    "list": [
      "Bandit Camp",
      "Black Knights' Fortress"
    ],
    "west": "Trollheim",
    "south": "Black Knights' Fortress (location)",
    "east": "Ferox Enclave",
    "template": "relative location"
  },
  {
    "location": "Darkmeyer",
    "north": "Haunted Woods",
    "west": "Mort Myre Swamp",
    "south": "Meiyerditch",
    "east": "Slepe",
    "template": "relative location"
  },
  {
    "location": "Demonic Ruins",
    "north": "Rogues' Castle",
    "west": "Spiders' Hill",
    "south": "Callisto's Den",
    "east": "Fountain of Rune",
    "template": "relative location"
  },
  {
    "location": "Digsite",
    "north": "Silvarea",
    "west": "Varrock",
    "south": "Exam Centre",
    "east": "River Salve",
    "template": "relative location"
  },
  {
    "location": "Draynor Manor",
    "north": "Barbarian Village",
    "east": "Champions' Guild",
    "south": "Draynor Village",
    "west": "Falador",
    "template": "relative location"
  },
  {
    "north": "Mage Training Arena",
    "south": "Citharede Abbey",
    "west": "Al Kharid Mine",
    "east": "River Salve",
    "template": "relative location"
  },
  {
    "name": "Ectofuntus",
    "north": "Unknown",
    "south": "Port Phasmatys",
    "east": "Dragontooth Island",
    "west": "Fenkenstrain's Castle",
    "float": "right",
    "template": "relative location"
  },
  {
    "location": "Ferox Enclave",
    "north": "Graveyard of Shadows",
    "west": "Dark Warriors' Fortress",
    "south": "Grand Exchange",
    "east": "Chaos Temple (Wilderness)",
    "template": "relative location"
  },
  {
    "location": "Rellekka Slayer Dungeon",
    "north": "Mountain Camp",
    "west": "Golden Apple Tree",
    "south": "Sinclair Mansion",
    "east": "Troll Stronghold",
    "template": "relative location"
  },
  {
    "location": "Grand Exchange",
    "north": "Wilderness",
    "south": "Cooks' Guild",
    "east": "Varrock Palace",
    "west": "Edgeville",
    "template": "relative location"
  },
  {
    "location": "Gwenith Hunter area",
    "north": "Gorlah",
    "south": "Prifddinas",
    "east": "Arandar",
    "west": "Gwenith",
    "template": "relative location"
  },
  {
    "location": "Haunted Woods",
    "north": "Fenkenstrain's Castle",
    "west": "Canifis",
    "south": "Darkmeyer",
    "east": "Port Phasmatys",
    "template": "relative location"
  },
  {
    "location": "Iorwerth Camp",
    "north": "Prifddinas",
    "east": "Arandar",
    "south": "Isafdar",
    "west": "Unknown",
    "template": "relative location"
  },
  {
    "name": "Keldagrim",
    "north": "Trollweiss and Rellekka Hunter area",
    "south": "Seers' Village",
    "east": "Mountain Camp",
    "west": "Rellekka",
    "template": "relative location"
  },
  {
    "location": "Kingstown",
    "north": "Arceuus",
    "south": "Hosidius",
    "east": "Hosidius",
    "west": "Kourend Castle",
    "template": "relative location"
  },
  {
    "location": "Land's End",
    "north": "Kourend Woodland",
    "west": "Unknown",
    "south": "Western Sea",
    "east": "Hosidius",
    "template": "relative location"
  },
  {
    "north": "Wilderness",
    "east": "Paterdomus",
    "south": "Tolna's rift",
    "west": "Jolly Boar Inn",
    "template": "relative location"
  },
  {
    "location": "Lumbridge",
    "north": "Varrock",
    "east": "Al Kharid",
    "south": "Lumbridge Swamp",
    "west": "Draynor Village",
    "template": "relative location"
  },
  {
    "location": "Lumbridge Castle",
    "north": "Varrock",
    "south": "Lumbridge Swamp",
    "east": "Al Kharid",
    "west": "Draynor Village",
    "template": "relative location"
  },
  {
    "location": "Lumbridge Swamp",
    "north": "Lumbridge",
    "west": "Wizards' Tower",
    "south": "Kalphite Lair",
    "east": "Al Kharid",
    "template": "relative location"
  },
  {
    "location": "Mage Arena",
    "north": "Northern Sea",
    "west": "Pirates' Hideout",
    "south": "Lava Maze",
    "east": "Rogues' Castle",
    "template": "relative location"
  },
  {
    "location": "McGrubor's Wood",
    "north": "Lighthouse",
    "west": "Coal Trucks",
    "south": "Hemenster",
    "east": "Seers' Village",
    "template": "relative location"
  },
  {
    "location": "Misthalin Manor",
    "north": "Lumbridge Swamp",
    "south": "Southern Sea",
    "template": "relative location"
  },
  {
    "location": "Mort'ton",
    "north": "Mort Myre Swamp",
    "west": "Kharidian Desert",
    "south": "Burgh de Rott",
    "east": "Barrows",
    "template": "relative location"
  },
  {
    "location": "Mort Myre Swamp",
    "north": "Canifis",
    "west": "River Salve",
    "south": "Mort'ton",
    "east": "Castle Drakan",
    "template": "relative location"
  },
  {
    "location": "Morytania",
    "north": "Fossil Island",
    "west": "Kingdom of Misthalin",
    "south": "Mos Le'Harmless",
    "template": "relative location"
  },
  {
    "location": "Mount Quidamortem",
    "north": "Kebos Swamp",
    "east": "Lizardman Settlement",
    "south": "The Stranglewood",
    "west": "Unknown",
    "template": "relative location"
  },
  {
    "location": "Northern Sea",
    "east": "Lithkren",
    "south": "Wilderness",
    "west": "Lunar Sea",
    "template": "relative location"
  },
  {
    "name": "Paterdomus Temple",
    "location": "Paterdomus Temple",
    "north": "Slayer Tower",
    "west": "Silvarea",
    "south": "Mort Myre Swamp",
    "east": "Canifis",
    "template": "relative location"
  },
  {
    "location": "Pirates' Hideout",
    "north": "Northern Sea",
    "west": "Wilderness Agility Course",
    "south": "Deep Wilderness Dungeon",
    "east": "Mage Arena",
    "template": "relative location"
  },
  {
    "location": "Falconer",
    "north": "Piscatoris Fishing Colony",
    "west": "Piscatoris Hunter area",
    "south": "Tree Gnome Stronghold",
    "east": "Barbarian Assault",
    "template": "relative location"
  },
  {
    "location": "Port Phasmatys",
    "north": "Fossil Island",
    "west": "Haunted Woods",
    "south": "Slepe",
    "east": "Dragontooth Island",
    "template": "relative location"
  },
  {
    "location": "Ranging Guild",
    "north": "Seers' Village",
    "west": "Fishing Guild",
    "south": "East Ardougne",
    "east": "Sorcerer's Tower",
    "template": "relative location"
  },
  {
    "location": "Resource Area",
    "north": "Magic axe hut",
    "west": "Deserted Keep",
    "south": "Lava Dragon Isle",
    "east": "Scorpion Pit",
    "template": "relative location"
  },
  {
    "location": "Rogues' Castle",
    "north": "Northern Sea",
    "west": "Scorpion Pit",
    "south": "Demonic Ruins",
    "east": "Wilderness Volcano",
    "template": "relative location"
  },
  {
    "north": "Northern Sea",
    "west": "Resource Area",
    "location": "Scorpion Pit",
    "east": "Rogues' Castle",
    "south": "Lava Dragon Isle",
    "template": "relative location"
  },
  {
    "location": "Shantay Pass",
    "north": "Al Kharid",
    "east": "Sorceress's Garden",
    "south": "Kharidian Desert",
    "west": "River Lum",
    "template": "relative location"
  },
  {
    "location": "Shilo Village",
    "north": "Tai Bwo Wannai",
    "west": "Cairn Isle",
    "south": "Kharazi Jungle",
    "east": "Ship Yard",
    "template": "relative location"
  },
  {
    "location": "Slepe",
    "north": "Port Phasmatys",
    "west": "Meiyerditch",
    "south": "Ver Sinhaza",
    "east": "Eastern Sea",
    "template": "relative location"
  },
  {
    "location": "Sorceress's Garden",
    "north": "Al Kharid",
    "west": "Shantay Pass",
    "south": "Kharidian Desert",
    "template": "relative location"
  },
  {
    "location": "Falador farm",
    "north": "Falador",
    "west": "Crafting Guild",
    "south": "Port Sarim",
    "east": "Draynor Village",
    "template": "relative location"
  },
  {
    "location": "Tai Bwo Wannai",
    "north": "Brimhaven",
    "east": "Ship yard",
    "south": "Shilo Village (location)",
    "list": [
      "Shilo Village"
    ],
    "west": "Yanille",
    "template": "relative location"
  },
  {
    "location": "The Stranglewood",
    "north": "Mount Quidamortem",
    "east": "Varlamore",
    "south": "Varlamore",
    "west": "Unknown",
    "template": "relative location"
  },
  {
    "location": "Tree Gnome Stronghold",
    "north": "Piscatoris Fishing Colony",
    "east": "Baxtorian Falls",
    "south": "Ardougne",
    "west": "Eagles' Peak (mountain)",
    "template": "relative location"
  },
  {
    "location": "Varrock Museum",
    "north": "Varrock Church",
    "east": "Digsite",
    "south": "Varrock east bank",
    "west": "Varrock Palace",
    "template": "relative location"
  },
  {
    "location": "Varrock Palace",
    "north": "Chaos Temple (Wilderness)",
    "south": "Varrock Square",
    "east": "Varrock Museum",
    "west": "Grand Exchange",
    "template": "relative location"
  },
  {
    "location": "Varrock Sewer",
    "north": "Wilderness",
    "west": "Varrock Palace",
    "south": "Varrock east bank",
    "east": "Varrock Museum",
    "template": "relative location"
  },
  {
    "location": "Ver Sinhaza",
    "north": "Slepe",
    "east": "Eastern Sea",
    "south": "Icyene Graveyard",
    "west": "Meiyerditch",
    "template": "relative location"
  },
  {
    "location": "Warriors' Guild",
    "north": "Death Plateau (location)",
    "list": [
      "Death Plateau"
    ],
    "east": "Burthorpe",
    "south": "White Wolf Mountain",
    "west": "Sinclair Mansion",
    "template": "relative location"
  },
  {
    "location": "Watson's house",
    "north": "Mess",
    "south": "Woodcutting guild",
    "east": "Forthos Ruin",
    "west": "Shayzien",
    "template": "relative location"
  },
  {
    "north": "Lava Maze",
    "west": "The Forgotten Cemetery",
    "location": "Wilderness God Wars Dungeon",
    "east": "Ruins",
    "south": "Bandit Camp (Wilderness)",
    "template": "relative location"
  },
  {
    "location": "Wilderness Volcano",
    "north": "Northern Sea",
    "east": "Fossil Island",
    "south": "Fountain of Rune",
    "west": "Rogues' Castle",
    "template": "relative location"
  },
  {
    "location": "Xeric's Shrine",
    "north": "Molch",
    "east": "Shayzien",
    "south": "Lizardman Settlement",
    "west": "Mount Quidamortem",
    "template": "relative location"
  }
]