[
  {
    "list": [
      "Post",
      "giving the same examine text"
    ],
    "template": "rscl"
  },
  {
    "list": [
      "certificates"
    ],
    "template": "rscl"
  },
  {
    "list": [
      "certificate"
    ],
    "template": "rscl"
  },
  {
    "list": [
      "Transcript:Watchtower wizard",
      "Watchtower Wizard"
    ],
    "template": "rscl"
  },
  {
    "list": [
      "RuneScape Classic"
    ],
    "template": "rscl"
  },
  {
    "list": [
      "RuneScape Classic"
    ],
    "template": "rscl"
  },
  {
    "list": [
      "Jakut"
    ],
    "template": "rscl"
  },
  {
    "list": [
      "certificates"
    ],
    "template": "rscl"
  },
  {
    "list": [
      "Dwarf multicannon",
      "multicannon"
    ],
    "template": "rscl"
  },
  {
    "list": [
      "Life-Rune"
    ],
    "xt": "life rune",
    "template": "rscl"
  },
  {
    "list": [
      "tailoring",
      "tailoring skill"
    ],
    "template": "rscl"
  },
  {
    "list": [
      "certificates"
    ],
    "template": "rscl"
  }
]